{"general": {"AudioFilename": "audio.mp3\n", "AudioLeadIn": "0\n", "PreviewTime": "96100\n", "Countdown": "0\n", "SampleSet": "Soft\n", "StackLeniency": "0.7\n", "Mode": "3\n", "LetterboxInBreaks": "0\n", "SpecialStyle": "0\n", "WidescreenStoryboard": "0\n", "SamplesMatchPlaybackRate": "1\n", "DistanceSpacing": "0.8\n", "BeatDivisor": "4\n", "GridSize": "8\n", "TimelineZoom": "1.3\n"}, "metadata": {"Title": "Final Boss\n", "TitleUnicode": "Final Boss\n", "Artist": "Thaehan\n", "ArtistUnicode": "Thaehan\n", "Creator": "AHHHHHHHHHHHHHH\n", "Version": "Second Stage\n", "Source": "osu!\n", "Tags": "Power up Electronic chiptune Featured Artist Loki 8Bit Baroque\n", "BeatmapID": "1312979\n", "BeatmapSetID": "622417\n"}, "difficulty": {"HPDrainRate": "7\n", "CircleSize": "4\n", "OverallDifficulty": "7.5\n", "ApproachRate": "5\n", "SliderMultiplier": "1.4\n", "SliderTickRate": "1\n"}, "timingpoints": [{"offset": "100", "millperbeat": "461.538461538462"}, {"offset": "7484", "millperbeat": "-100"}, {"offset": "14811", "millperbeat": "-100"}, {"offset": "14869", "millperbeat": "-100"}, {"offset": "22253", "millperbeat": "-100"}, {"offset": "59176", "millperbeat": "-100"}, {"offset": "66446", "millperbeat": "-100"}, {"offset": "66561", "millperbeat": "-100"}, {"offset": "73023", "millperbeat": "-100"}, {"offset": "96100", "millperbeat": "-100"}, {"offset": "103369", "millperbeat": "-100"}, {"offset": "103484", "millperbeat": "-100"}, {"offset": "110869", "millperbeat": "-100"}], "hitobjects": [{"x": "64", "y": "192", "time": "100", "type": "128", "hitsound": "0", "extras": "330:0:0:0:0:\n"}, {"x": "192", "y": "192", "time": "330", "type": "128", "hitsound": "0", "extras": "561:0:0:0:0:\n"}, {"x": "448", "y": "192", "time": "561", "type": "1", "hitsound": "0", "extras": "0:0:0:0:\n"}, {"x": "320", "y": "192", "time": "676", "type": "1", "hitsound": "0", "extras": "0:0:0:0:\n"}, {"x": "192", "y": "192", "time": "792", "type": "1", "hitsound": "0", "extras": "0:0:0:0:\n"}, {"x": "64", "y": "192", "time": "907", "type": "1", "hitsound": "0", "extras": "0:0:0:0:\n"}, {"x": "448", "y": "192", "time": "1023", "type": "128", "hitsound": "0", "extras": "1253:0:0:0:0:\n"}, {"x": "320", "y": "192", "time": "1253", "type": "1", "hitsound": "0", "extras": "0:0:0:0:\n"}, {"x": "64", "y": "192", "time": "1484", "type": "128", "hitsound": "0", "extras": "1715:0:0:0:0:\n"}, {"x": "192", "y": "192", "time": "1715", "type": "1", "hitsound": "0", "extras": "0:0:0:0:\n"}, {"x": "64", "y": "192", "time": "2061", "type": "1", "hitsound": "0", "extras": "0:0:0:0:\n"}, {"x": "192", "y": "192", "time": "2176", "type": "1", "hitsound": "0", "extras": "0:0:0:0:\n"}, {"x": "448", "y": "192", "time": "2292", "type": "1", "hitsound": "0", "extras": "0:0:0:0:\n"}, {"x": "320", "y": "192", "time": "2407", "type": "1", "hitsound": "0", "extras": "0:0:0:0:\n"}, {"x": "192", "y": "192", "time": "2523", "type": "1", "hitsound": "0", "extras": "0:0:0:0:\n"}, {"x": "64", "y": "192", "time": "2638", "type": "1", "hitsound": "0", "extras": "0:0:0:0:\n"}, {"x": "448", "y": "192", "time": "2753", "type": "1", "hitsound": "0", "extras": "0:0:0:0:\n"}, {"x": "192", "y": "192", "time": "2869", "type": "1", "hitsound": "0", "extras": "0:0:0:0:\n"}, {"x": "448", "y": "192", "time": "2984", "type": "1", "hitsound": "0", "extras": "0:0:0:0:\n"}, {"x": "64", "y": "192", "time": "3100", "type": "1", "hitsound": "0", "extras": "0:0:0:0:\n"}, {"x": "320", "y": "192", "time": "3215", "type": "1", "hitsound": "0", "extras": "0:0:0:0:\n"}, {"x": "64", "y": "192", "time": "3330", "type": "1", "hitsound": "0", "extras": "0:0:0:0:\n"}, {"x": "448", "y": "192", "time": "3446", "type": "1", "hitsound": "0", "extras": "0:0:0:0:\n"}, {"x": "192", "y": "192", "time": "3561", "type": "1", "hitsound": "0", "extras": "0:0:0:0:\n"}, {"x": "448", "y": "192", "time": "3676", "type": "1", "hitsound": "0", "extras": "0:0:0:0:\n"}, {"x": "320", "y": "192", "time": "3792", "type": "128", "hitsound": "0", "extras": "4023:0:0:0:0:\n"}, {"x": "64", "y": "192", "time": "4023", "type": "128", "hitsound": "0", "extras": "4253:0:0:0:0:\n"}, {"x": "192", "y": "192", "time": "4253", "type": "1", "hitsound": "0", "extras": "0:0:0:0:\n"}, {"x": "448", "y": "192", "time": "4369", "type": "1", "hitsound": "0", "extras": "0:0:0:0:\n"}, {"x": "64", "y": "192", "time": "4484", "type": "1", "hitsound": "0", "extras": "0:0:0:0:\n"}, {"x": "192", "y": "192", "time": "4600", "type": "1", "hitsound": "0", "extras": "0:0:0:0:\n"}, {"x": "320", "y": "192", "time": "4715", "type": "128", "hitsound": "0", "extras": "4946:0:0:0:0:\n"}, {"x": "448", "y": "192", "time": "4946", "type": "128", "hitsound": "0", "extras": "5176:0:0:0:0:\n"}, {"x": "192", "y": "192", "time": "5176", "type": "128", "hitsound": "0", "extras": "5407:0:0:0:0:\n"}, {"x": "64", "y": "192", "time": "5407", "type": "128", "hitsound": "0", "extras": "5638:0:0:0:0:\n"}, {"x": "320", "y": "192", "time": "5638", "type": "1", "hitsound": "0", "extras": "0:0:0:0:\n"}, {"x": "448", "y": "192", "time": "5753", "type": "1", "hitsound": "0", "extras": "0:0:0:0:\n"}, {"x": "320", "y": "192", "time": "5869", "type": "1", "hitsound": "0", "extras": "0:0:0:0:\n"}, {"x": "192", "y": "192", "time": "5984", "type": "1", "hitsound": "0", "extras": "0:0:0:0:\n"}, {"x": "64", "y": "192", "time": "6100", "type": "1", "hitsound": "0", "extras": "0:0:0:0:\n"}, {"x": "192", "y": "192", "time": "6215", "type": "1", "hitsound": "0", "extras": "0:0:0:0:\n"}, {"x": "320", "y": "192", "time": "6330", "type": "1", "hitsound": "0", "extras": "0:0:0:0:\n"}, {"x": "448", "y": "192", "time": "6446", "type": "1", "hitsound": "0", "extras": "0:0:0:0:\n"}, {"x": "64", "y": "192", "time": "6561", "type": "1", "hitsound": "0", "extras": "0:0:0:0:\n"}, {"x": "192", "y": "192", "time": "6676", "type": "1", "hitsound": "0", "extras": "0:0:0:0:\n"}, {"x": "320", "y": "192", "time": "6792", "type": "1", "hitsound": "0", "extras": "0:0:0:0:\n"}, {"x": "448", "y": "192", "time": "6907", "type": "1", "hitsound": "0", "extras": "0:0:0:0:\n"}, {"x": "320", "y": "192", "time": "7023", "type": "1", "hitsound": "0", "extras": "0:0:0:0:\n"}, {"x": "192", "y": "192", "time": "7138", "type": "1", "hitsound": "0", "extras": "0:0:0:0:\n"}, {"x": "448", "y": "192", "time": "7253", "type": "1", "hitsound": "0", "extras": "0:0:0:0:\n"}, {"x": "64", "y": "192", "time": "7369", "type": "1", "hitsound": "0", "extras": "0:0:0:0:\n"}, {"x": "320", "y": "192", "time": "7484", "type": "1", "hitsound": "2", "extras": "1:2:0:0:\n"}, {"x": "192", "y": "192", "time": "7484", "type": "128", "hitsound": "4", "extras": "7715:0:0:0:0:\n"}, {"x": "64", "y": "192", "time": "7715", "type": "128", "hitsound": "0", "extras": "7946:0:0:0:0:\n"}, {"x": "448", "y": "192", "time": "7946", "type": "1", "hitsound": "2", "extras": "0:0:0:0:\n"}, {"x": "320", "y": "192", "time": "8061", "type": "1", "hitsound": "0", "extras": "0:0:0:0:\n"}, {"x": "192", "y": "192", "time": "8176", "type": "1", "hitsound": "0", "extras": "0:0:0:0:\n"}, {"x": "64", "y": "192", "time": "8292", "type": "1", "hitsound": "0", "extras": "0:0:0:0:\n"}, {"x": "320", "y": "192", "time": "8407", "type": "128", "hitsound": "4", "extras": "8638:0:0:0:0:\n"}, {"x": "192", "y": "192", "time": "8638", "type": "128", "hitsound": "0", "extras": "8869:0:0:0:0:\n"}, {"x": "448", "y": "192", "time": "8869", "type": "128", "hitsound": "2", "extras": "9100:0:0:0:0:\n"}, {"x": "64", "y": "192", "time": "9100", "type": "128", "hitsound": "0", "extras": "9330:0:0:0:0:\n"}, {"x": "448", "y": "192", "time": "9330", "type": "1", "hitsound": "4", "extras": "0:0:0:0:\n"}, {"x": "192", "y": "192", "time": "9446", "type": "1", "hitsound": "0", "extras": "0:0:0:0:\n"}, {"x": "320", "y": "192", "time": "9561", "type": "1", "hitsound": "0", "extras": "0:0:0:0:\n"}, {"x": "448", "y": "192", "time": "9676", "type": "1", "hitsound": "0", "extras": "0:0:0:0:\n"}, {"x": "64", "y": "192", "time": "9792", "type": "1", "hitsound": "2", "extras": "0:0:0:0:\n"}, {"x": "192", "y": "192", "time": "9907", "type": "1", "hitsound": "0", "extras": "0:0:0:0:\n"}, {"x": "320", "y": "192", "time": "10023", "type": "1", "hitsound": "0", "extras": "0:0:0:0:\n"}, {"x": "448", "y": "192", "time": "10138", "type": "1", "hitsound": "0", "extras": "0:0:0:0:\n"}, {"x": "64", "y": "192", "time": "10253", "type": "128", "hitsound": "4", "extras": "10484:0:0:0:0:\n"}, {"x": "320", "y": "192", "time": "10484", "type": "128", "hitsound": "0", "extras": "10715:0:0:0:0:\n"}, {"x": "192", "y": "192", "time": "10715", "type": "128", "hitsound": "2", "extras": "10946:0:0:0:0:\n"}, {"x": "448", "y": "192", "time": "10946", "type": "128", "hitsound": "0", "extras": "11176:0:0:0:0:\n"}, {"x": "320", "y": "192", "time": "11176", "type": "128", "hitsound": "4", "extras": "11407:0:0:0:0:\n"}, {"x": "192", "y": "192", "time": "11407", "type": "128", "hitsound": "0", "extras": "11638:0:0:0:0:\n"}, {"x": "448", "y": "192", "time": "11638", "type": "1", "hitsound": "2", "extras": "0:0:0:0:\n"}, {"x": "64", "y": "192", "time": "11753", "type": "1", "hitsound": "0", "extras": "0:0:0:0:\n"}, {"x": "320", "y": "192", "time": "11869", "type": "1", "hitsound": "0", "extras": "0:0:0:0:\n"}, {"x": "192", "y": "192", "time": "11984", "type": "1", "hitsound": "0", "extras": "0:0:0:0:\n"}, {"x": "64", "y": "192", "time": "12100", "type": "128", "hitsound": "4", "extras": "12330:0:0:0:0:\n"}, {"x": "448", "y": "192", "time": "12330", "type": "128", "hitsound": "0", "extras": "12561:0:0:0:0:\n"}, {"x": "192", "y": "192", "time": "12561", "type": "128", "hitsound": "2", "extras": "12792:0:0:0:0:\n"}, {"x": "320", "y": "192", "time": "12792", "type": "128", "hitsound": "0", "extras": "13023:0:0:0:0:\n"}, {"x": "64", "y": "192", "time": "13023", "type": "1", "hitsound": "4", "extras": "0:0:0:0:\n"}, {"x": "448", "y": "192", "time": "13138", "type": "1", "hitsound": "0", "extras": "0:0:0:0:\n"}, {"x": "320", "y": "192", "time": "13253", "type": "1", "hitsound": "0", "extras": "0:0:0:0:\n"}, {"x": "64", "y": "192", "time": "13369", "type": "1", "hitsound": "0", "extras": "0:0:0:0:\n"}, {"x": "192", "y": "192", "time": "13484", "type": "1", "hitsound": "2", "extras": "0:0:0:0:\n"}, {"x": "448", "y": "192", "time": "13600", "type": "1", "hitsound": "0", "extras": "0:0:0:0:\n"}, {"x": "320", "y": "192", "time": "13715", "type": "1", "hitsound": "0", "extras": "0:0:0:0:\n"}, {"x": "448", "y": "192", "time": "13830", "type": "1", "hitsound": "0", "extras": "0:0:0:0:\n"}, {"x": "192", "y": "192", "time": "13946", "type": "128", "hitsound": "0", "extras": "14176:0:0:0:0:\n"}, {"x": "64", "y": "192", "time": "13946", "type": "1", "hitsound": "4", "extras": "0:0:0:0:\n"}, {"x": "320", "y": "192", "time": "14176", "type": "128", "hitsound": "0", "extras": "14407:0:0:0:0:\n"}, {"x": "448", "y": "192", "time": "14407", "type": "128", "hitsound": "0", "extras": "14638:0:0:0:0:\n"}, {"x": "192", "y": "192", "time": "14407", "type": "1", "hitsound": "2", "extras": "0:0:0:0:\n"}, {"x": "64", "y": "192", "time": "14638", "type": "128", "hitsound": "0", "extras": "14869:0:0:0:0:\n"}, {"x": "192", "y": "192", "time": "14869", "type": "1", "hitsound": "4", "extras": "0:0:0:0:\n"}, {"x": "320", "y": "192", "time": "14869", "type": "128", "hitsound": "0", "extras": "15100:0:0:0:0:\n"}, {"x": "448", "y": "192", "time": "15100", "type": "128", "hitsound": "0", "extras": "15330:0:0:0:0:\n"}, {"x": "64", "y": "192", "time": "15330", "type": "1", "hitsound": "2", "extras": "0:0:0:0:\n"}, {"x": "192", "y": "192", "time": "15446", "type": "1", "hitsound": "0", "extras": "0:0:0:0:\n"}, {"x": "320", "y": "192", "time": "15561", "type": "1", "hitsound": "0", "extras": "0:0:0:0:\n"}, {"x": "448", "y": "192", "time": "15676", "type": "1", "hitsound": "0", "extras": "0:0:0:0:\n"}, {"x": "64", "y": "192", "time": "15792", "type": "128", "hitsound": "4", "extras": "16023:0:0:0:0:\n"}, {"x": "320", "y": "192", "time": "16023", "type": "128", "hitsound": "0", "extras": "16253:0:0:0:0:\n"}, {"x": "192", "y": "192", "time": "16253", "type": "128", "hitsound": "2", "extras": "16484:0:0:0:0:\n"}, {"x": "448", "y": "192", "time": "16484", "type": "128", "hitsound": "0", "extras": "16715:0:0:0:0:\n"}, {"x": "320", "y": "192", "time": "16715", "type": "1", "hitsound": "4", "extras": "0:0:0:0:\n"}, {"x": "64", "y": "192", "time": "16830", "type": "1", "hitsound": "0", "extras": "0:0:0:0:\n"}, {"x": "192", "y": "192", "time": "16946", "type": "1", "hitsound": "0", "extras": "0:0:0:0:\n"}, {"x": "320", "y": "192", "time": "17061", "type": "1", "hitsound": "0", "extras": "0:0:0:0:\n"}, {"x": "448", "y": "192", "time": "17176", "type": "1", "hitsound": "2", "extras": "0:0:0:0:\n"}, {"x": "320", "y": "192", "time": "17292", "type": "1", "hitsound": "0", "extras": "0:0:0:0:\n"}, {"x": "192", "y": "192", "time": "17407", "type": "1", "hitsound": "0", "extras": "0:0:0:0:\n"}, {"x": "64", "y": "192", "time": "17523", "type": "1", "hitsound": "0", "extras": "0:0:0:0:\n"}, {"x": "448", "y": "192", "time": "17638", "type": "128", "hitsound": "4", "extras": "17869:0:0:0:0:\n"}, {"x": "192", "y": "192", "time": "17869", "type": "128", "hitsound": "0", "extras": "18100:0:0:0:0:\n"}, {"x": "320", "y": "192", "time": "18100", "type": "128", "hitsound": "2", "extras": "18330:0:0:0:0:\n"}, {"x": "64", "y": "192", "time": "18330", "type": "128", "hitsound": "0", "extras": "18561:0:0:0:0:\n"}, {"x": "448", "y": "192", "time": "18561", "type": "128", "hitsound": "4", "extras": "18792:0:0:0:0:\n"}, {"x": "192", "y": "192", "time": "18792", "type": "128", "hitsound": "0", "extras": "19023:0:0:0:0:\n"}, {"x": "320", "y": "192", "time": "19023", "type": "1", "hitsound": "2", "extras": "0:0:0:0:\n"}, {"x": "448", "y": "192", "time": "19138", "type": "1", "hitsound": "0", "extras": "0:0:0:0:\n"}, {"x": "64", "y": "192", "time": "19253", "type": "1", "hitsound": "0", "extras": "0:0:0:0:\n"}, {"x": "192", "y": "192", "time": "19369", "type": "1", "hitsound": "0", "extras": "0:0:0:0:\n"}, {"x": "320", "y": "192", "time": "19484", "type": "128", "hitsound": "4", "extras": "19715:0:0:0:0:\n"}, {"x": "448", "y": "192", "time": "19715", "type": "128", "hitsound": "0", "extras": "19946:0:0:0:0:\n"}, {"x": "64", "y": "192", "time": "19946", "type": "128", "hitsound": "2", "extras": "20176:0:0:0:0:\n"}, {"x": "192", "y": "192", "time": "20176", "type": "128", "hitsound": "0", "extras": "20407:0:0:0:0:\n"}, {"x": "320", "y": "192", "time": "20407", "type": "1", "hitsound": "4", "extras": "0:0:0:0:\n"}, {"x": "448", "y": "192", "time": "20523", "type": "1", "hitsound": "0", "extras": "0:0:0:0:\n"}, {"x": "64", "y": "192", "time": "20638", "type": "1", "hitsound": "0", "extras": "0:0:0:0:\n"}, {"x": "192", "y": "192", "time": "20753", "type": "1", "hitsound": "0", "extras": "0:0:0:0:\n"}, {"x": "320", "y": "192", "time": "20869", "type": "1", "hitsound": "4", "extras": "0:0:0:0:\n"}, {"x": "192", "y": "192", "time": "20984", "type": "1", "hitsound": "0", "extras": "0:0:0:0:\n"}, {"x": "64", "y": "192", "time": "21100", "type": "1", "hitsound": "0", "extras": "0:0:0:0:\n"}, {"x": "448", "y": "192", "time": "21215", "type": "1", "hitsound": "0", "extras": "0:0:0:0:\n"}, {"x": "320", "y": "192", "time": "21330", "type": "1", "hitsound": "4", "extras": "0:0:0:0:\n"}, {"x": "192", "y": "192", "time": "21446", "type": "1", "hitsound": "0", "extras": "0:0:0:0:\n"}, {"x": "320", "y": "192", "time": "21561", "type": "1", "hitsound": "0", "extras": "0:0:0:0:\n"}, {"x": "448", "y": "192", "time": "21676", "type": "1", "hitsound": "0", "extras": "0:0:0:0:\n"}, {"x": "64", "y": "192", "time": "21792", "type": "1", "hitsound": "0", "extras": "0:0:0:0:\n"}, {"x": "192", "y": "192", "time": "21907", "type": "1", "hitsound": "0", "extras": "0:0:0:0:\n"}, {"x": "320", "y": "192", "time": "22023", "type": "1", "hitsound": "0", "extras": "0:0:0:0:\n"}, {"x": "448", "y": "192", "time": "22138", "type": "1", "hitsound": "0", "extras": "0:0:0:0:\n"}, {"x": "320", "y": "192", "time": "22253", "type": "1", "hitsound": "4", "extras": "0:0:0:0:\n"}, {"x": "192", "y": "192", "time": "22484", "type": "1", "hitsound": "0", "extras": "0:0:0:0:\n"}, {"x": "320", "y": "192", "time": "22715", "type": "1", "hitsound": "4", "extras": "0:0:0:0:\n"}, {"x": "64", "y": "192", "time": "22830", "type": "1", "hitsound": "0", "extras": "0:0:0:0:\n"}, {"x": "448", "y": "192", "time": "22946", "type": "1", "hitsound": "0", "extras": "0:0:0:0:\n"}, {"x": "320", "y": "192", "time": "23061", "type": "1", "hitsound": "0", "extras": "0:0:0:0:\n"}, {"x": "192", "y": "192", "time": "23176", "type": "1", "hitsound": "4", "extras": "0:0:0:0:\n"}, {"x": "448", "y": "192", "time": "23407", "type": "1", "hitsound": "0", "extras": "0:0:0:0:\n"}, {"x": "320", "y": "192", "time": "23638", "type": "1", "hitsound": "4", "extras": "0:0:0:0:\n"}, {"x": "192", "y": "192", "time": "23869", "type": "1", "hitsound": "0", "extras": "0:0:0:0:\n"}, {"x": "64", "y": "192", "time": "24100", "type": "1", "hitsound": "4", "extras": "0:0:0:0:\n"}, {"x": "320", "y": "192", "time": "24330", "type": "1", "hitsound": "0", "extras": "0:0:0:0:\n"}, {"x": "192", "y": "192", "time": "24561", "type": "1", "hitsound": "4", "extras": "0:0:0:0:\n"}, {"x": "448", "y": "192", "time": "24792", "type": "1", "hitsound": "0", "extras": "0:0:0:0:\n"}, {"x": "320", "y": "192", "time": "25023", "type": "1", "hitsound": "4", "extras": "0:0:0:0:\n"}, {"x": "192", "y": "192", "time": "25253", "type": "1", "hitsound": "0", "extras": "0:0:0:0:\n"}, {"x": "448", "y": "192", "time": "25484", "type": "1", "hitsound": "4", "extras": "0:0:0:0:\n"}, {"x": "64", "y": "192", "time": "25715", "type": "1", "hitsound": "0", "extras": "0:0:0:0:\n"}, {"x": "320", "y": "192", "time": "25946", "type": "1", "hitsound": "4", "extras": "0:0:0:0:\n"}, {"x": "64", "y": "192", "time": "26176", "type": "1", "hitsound": "0", "extras": "0:0:0:0:\n"}, {"x": "192", "y": "192", "time": "26407", "type": "1", "hitsound": "4", "extras": "0:0:0:0:\n"}, {"x": "320", "y": "192", "time": "26523", "type": "1", "hitsound": "0", "extras": "0:0:0:0:\n"}, {"x": "64", "y": "192", "time": "26638", "type": "1", "hitsound": "0", "extras": "0:0:0:0:\n"}, {"x": "192", "y": "192", "time": "26753", "type": "1", "hitsound": "0", "extras": "0:0:0:0:\n"}, {"x": "448", "y": "192", "time": "26869", "type": "1", "hitsound": "4", "extras": "0:0:0:0:\n"}, {"x": "320", "y": "192", "time": "27100", "type": "1", "hitsound": "0", "extras": "0:0:0:0:\n"}, {"x": "64", "y": "192", "time": "27330", "type": "1", "hitsound": "4", "extras": "0:0:0:0:\n"}, {"x": "448", "y": "192", "time": "27561", "type": "1", "hitsound": "0", "extras": "0:0:0:0:\n"}, {"x": "192", "y": "192", "time": "27792", "type": "1", "hitsound": "4", "extras": "0:0:0:0:\n"}, {"x": "320", "y": "192", "time": "28023", "type": "1", "hitsound": "0", "extras": "0:0:0:0:\n"}, {"x": "64", "y": "192", "time": "28253", "type": "1", "hitsound": "4", "extras": "0:0:0:0:\n"}, {"x": "448", "y": "192", "time": "28484", "type": "1", "hitsound": "0", "extras": "0:0:0:0:\n"}, {"x": "320", "y": "192", "time": "28715", "type": "1", "hitsound": "4", "extras": "0:0:0:0:\n"}, {"x": "192", "y": "192", "time": "28946", "type": "1", "hitsound": "0", "extras": "0:0:0:0:\n"}, {"x": "64", "y": "192", "time": "29176", "type": "1", "hitsound": "4", "extras": "0:0:0:0:\n"}, {"x": "192", "y": "192", "time": "29407", "type": "1", "hitsound": "4", "extras": "0:0:0:0:\n"}, {"x": "320", "y": "192", "time": "29523", "type": "1", "hitsound": "4", "extras": "0:0:0:0:\n"}, {"x": "448", "y": "192", "time": "29638", "type": "1", "hitsound": "4", "extras": "0:0:0:0:\n"}, {"x": "192", "y": "192", "time": "29869", "type": "1", "hitsound": "0", "extras": "0:0:0:0:\n"}, {"x": "64", "y": "192", "time": "30100", "type": "1", "hitsound": "2", "extras": "0:0:0:0:\n"}, {"x": "192", "y": "192", "time": "30215", "type": "1", "hitsound": "0", "extras": "0:0:0:0:\n"}, {"x": "320", "y": "192", "time": "30330", "type": "1", "hitsound": "0", "extras": "0:0:0:0:\n"}, {"x": "448", "y": "192", "time": "30446", "type": "1", "hitsound": "0", "extras": "0:0:0:0:\n"}, {"x": "320", "y": "192", "time": "30561", "type": "1", "hitsound": "4", "extras": "0:0:0:0:\n"}, {"x": "192", "y": "192", "time": "30676", "type": "1", "hitsound": "0", "extras": "0:0:0:0:\n"}, {"x": "64", "y": "192", "time": "30792", "type": "1", "hitsound": "0", "extras": "0:0:0:0:\n"}, {"x": "448", "y": "192", "time": "30907", "type": "1", "hitsound": "0", "extras": "0:0:0:0:\n"}, {"x": "320", "y": "192", "time": "31023", "type": "1", "hitsound": "2", "extras": "0:0:0:0:\n"}, {"x": "192", "y": "192", "time": "31138", "type": "1", "hitsound": "0", "extras": "0:0:0:0:\n"}, {"x": "320", "y": "192", "time": "31253", "type": "1", "hitsound": "0", "extras": "0:0:0:0:\n"}, {"x": "192", "y": "192", "time": "31369", "type": "1", "hitsound": "0", "extras": "0:0:0:0:\n"}, {"x": "64", "y": "192", "time": "31484", "type": "1", "hitsound": "4", "extras": "0:0:0:0:\n"}, {"x": "448", "y": "192", "time": "31715", "type": "1", "hitsound": "4", "extras": "0:0:0:0:\n"}, {"x": "192", "y": "192", "time": "31946", "type": "1", "hitsound": "2", "extras": "0:0:0:0:\n"}, {"x": "320", "y": "192", "time": "32176", "type": "1", "hitsound": "4", "extras": "0:0:0:0:\n"}, {"x": "64", "y": "192", "time": "32407", "type": "1", "hitsound": "4", "extras": "0:0:0:0:\n"}, {"x": "192", "y": "192", "time": "32638", "type": "1", "hitsound": "4", "extras": "0:0:0:0:\n"}, {"x": "320", "y": "192", "time": "32869", "type": "128", "hitsound": "2", "extras": "33100:0:0:0:0:\n"}, {"x": "448", "y": "192", "time": "33100", "type": "128", "hitsound": "0", "extras": "33330:0:0:0:0:\n"}, {"x": "192", "y": "192", "time": "33330", "type": "128", "hitsound": "4", "extras": "33561:0:0:0:0:\n"}, {"x": "64", "y": "192", "time": "33561", "type": "128", "hitsound": "0", "extras": "33792:0:0:0:0:\n"}, {"x": "448", "y": "192", "time": "33792", "type": "1", "hitsound": "2", "extras": "0:0:0:0:\n"}, {"x": "320", "y": "192", "time": "33907", "type": "1", "hitsound": "0", "extras": "0:0:0:0:\n"}, {"x": "192", "y": "192", "time": "34023", "type": "1", "hitsound": "0", "extras": "0:0:0:0:\n"}, {"x": "64", "y": "192", "time": "34138", "type": "1", "hitsound": "0", "extras": "0:0:0:0:\n"}, {"x": "192", "y": "192", "time": "34253", "type": "1", "hitsound": "4", "extras": "0:0:0:0:\n"}, {"x": "320", "y": "192", "time": "34369", "type": "1", "hitsound": "0", "extras": "0:0:0:0:\n"}, {"x": "448", "y": "192", "time": "34484", "type": "1", "hitsound": "0", "extras": "0:0:0:0:\n"}, {"x": "64", "y": "192", "time": "34600", "type": "1", "hitsound": "0", "extras": "0:0:0:0:\n"}, {"x": "192", "y": "192", "time": "34715", "type": "1", "hitsound": "2", "extras": "0:0:0:0:\n"}, {"x": "320", "y": "192", "time": "34830", "type": "1", "hitsound": "0", "extras": "0:0:0:0:\n"}, {"x": "192", "y": "192", "time": "34946", "type": "1", "hitsound": "0", "extras": "0:0:0:0:\n"}, {"x": "320", "y": "192", "time": "35061", "type": "1", "hitsound": "0", "extras": "0:0:0:0:\n"}, {"x": "448", "y": "192", "time": "35176", "type": "1", "hitsound": "4", "extras": "0:0:0:0:\n"}, {"x": "320", "y": "192", "time": "35407", "type": "1", "hitsound": "4", "extras": "0:0:0:0:\n"}, {"x": "192", "y": "192", "time": "35638", "type": "1", "hitsound": "4", "extras": "0:0:0:0:\n"}, {"x": "64", "y": "192", "time": "35869", "type": "1", "hitsound": "4", "extras": "0:0:0:0:\n"}, {"x": "192", "y": "192", "time": "36100", "type": "1", "hitsound": "4", "extras": "0:0:0:0:\n"}, {"x": "320", "y": "192", "time": "36330", "type": "1", "hitsound": "4", "extras": "0:0:0:0:\n"}, {"x": "448", "y": "192", "time": "36561", "type": "128", "hitsound": "2", "extras": "36792:0:0:0:0:\n"}, {"x": "64", "y": "192", "time": "36792", "type": "128", "hitsound": "4", "extras": "37023:0:0:0:0:\n"}, {"x": "192", "y": "192", "time": "37023", "type": "128", "hitsound": "4", "extras": "37253:0:0:0:0:\n"}, {"x": "320", "y": "192", "time": "37253", "type": "128", "hitsound": "0", "extras": "37484:0:0:0:0:\n"}, {"x": "64", "y": "192", "time": "37484", "type": "1", "hitsound": "2", "extras": "0:0:0:0:\n"}, {"x": "192", "y": "192", "time": "37600", "type": "1", "hitsound": "0", "extras": "0:0:0:0:\n"}, {"x": "448", "y": "192", "time": "37715", "type": "1", "hitsound": "0", "extras": "0:0:0:0:\n"}, {"x": "320", "y": "192", "time": "37830", "type": "1", "hitsound": "0", "extras": "0:0:0:0:\n"}, {"x": "64", "y": "192", "time": "37946", "type": "1", "hitsound": "4", "extras": "0:0:0:0:\n"}, {"x": "192", "y": "192", "time": "38061", "type": "1", "hitsound": "0", "extras": "0:0:0:0:\n"}, {"x": "448", "y": "192", "time": "38176", "type": "1", "hitsound": "0", "extras": "0:0:0:0:\n"}, {"x": "320", "y": "192", "time": "38292", "type": "1", "hitsound": "0", "extras": "0:0:0:0:\n"}, {"x": "64", "y": "192", "time": "38407", "type": "1", "hitsound": "2", "extras": "0:0:0:0:\n"}, {"x": "192", "y": "192", "time": "38523", "type": "1", "hitsound": "0", "extras": "0:0:0:0:\n"}, {"x": "448", "y": "192", "time": "38638", "type": "1", "hitsound": "0", "extras": "0:0:0:0:\n"}, {"x": "320", "y": "192", "time": "38753", "type": "1", "hitsound": "0", "extras": "0:0:0:0:\n"}, {"x": "64", "y": "192", "time": "38869", "type": "1", "hitsound": "4", "extras": "0:0:0:0:\n"}, {"x": "448", "y": "192", "time": "39100", "type": "1", "hitsound": "4", "extras": "0:0:0:0:\n"}, {"x": "192", "y": "192", "time": "39330", "type": "1", "hitsound": "2", "extras": "0:0:0:0:\n"}, {"x": "320", "y": "192", "time": "39561", "type": "1", "hitsound": "4", "extras": "0:0:0:0:\n"}, {"x": "64", "y": "192", "time": "39792", "type": "1", "hitsound": "4", "extras": "0:0:0:0:\n"}, {"x": "192", "y": "192", "time": "40023", "type": "1", "hitsound": "4", "extras": "0:0:0:0:\n"}, {"x": "448", "y": "192", "time": "40253", "type": "128", "hitsound": "2", "extras": "40484:0:0:0:0:\n"}, {"x": "64", "y": "192", "time": "40484", "type": "128", "hitsound": "0", "extras": "40715:0:0:0:0:\n"}, {"x": "320", "y": "192", "time": "40715", "type": "128", "hitsound": "4", "extras": "40946:0:0:0:0:\n"}, {"x": "192", "y": "192", "time": "40946", "type": "128", "hitsound": "0", "extras": "41176:0:0:0:0:\n"}, {"x": "320", "y": "192", "time": "41176", "type": "1", "hitsound": "2", "extras": "0:0:0:0:\n"}, {"x": "448", "y": "192", "time": "41292", "type": "1", "hitsound": "0", "extras": "0:0:0:0:\n"}, {"x": "192", "y": "192", "time": "41407", "type": "1", "hitsound": "0", "extras": "0:0:0:0:\n"}, {"x": "64", "y": "192", "time": "41523", "type": "1", "hitsound": "0", "extras": "0:0:0:0:\n"}, {"x": "320", "y": "192", "time": "41638", "type": "1", "hitsound": "4", "extras": "0:0:0:0:\n"}, {"x": "448", "y": "192", "time": "41753", "type": "1", "hitsound": "0", "extras": "0:0:0:0:\n"}, {"x": "192", "y": "192", "time": "41869", "type": "1", "hitsound": "0", "extras": "0:0:0:0:\n"}, {"x": "64", "y": "192", "time": "41984", "type": "1", "hitsound": "0", "extras": "0:0:0:0:\n"}, {"x": "320", "y": "192", "time": "42100", "type": "1", "hitsound": "2", "extras": "0:0:0:0:\n"}, {"x": "448", "y": "192", "time": "42215", "type": "1", "hitsound": "0", "extras": "0:0:0:0:\n"}, {"x": "192", "y": "192", "time": "42330", "type": "1", "hitsound": "0", "extras": "0:0:0:0:\n"}, {"x": "64", "y": "192", "time": "42446", "type": "1", "hitsound": "0", "extras": "0:0:0:0:\n"}, {"x": "448", "y": "192", "time": "42561", "type": "1", "hitsound": "4", "extras": "0:0:0:0:\n"}, {"x": "192", "y": "192", "time": "42792", "type": "1", "hitsound": "4", "extras": "0:0:0:0:\n"}, {"x": "320", "y": "192", "time": "43023", "type": "1", "hitsound": "4", "extras": "0:0:0:0:\n"}, {"x": "64", "y": "192", "time": "43253", "type": "1", "hitsound": "4", "extras": "0:0:0:0:\n"}, {"x": "192", "y": "192", "time": "43484", "type": "1", "hitsound": "4", "extras": "0:0:0:0:\n"}, {"x": "448", "y": "192", "time": "43715", "type": "1", "hitsound": "4", "extras": "0:0:0:0:\n"}, {"x": "320", "y": "192", "time": "43946", "type": "128", "hitsound": "0", "extras": "44176:0:0:0:0:\n"}, {"x": "64", "y": "192", "time": "44176", "type": "128", "hitsound": "0", "extras": "44407:0:0:0:0:\n"}, {"x": "192", "y": "192", "time": "44407", "type": "1", "hitsound": "0", "extras": "0:0:0:0:\n"}, {"x": "320", "y": "192", "time": "44638", "type": "1", "hitsound": "0", "extras": "0:0:0:0:\n"}, {"x": "448", "y": "192", "time": "44869", "type": "1", "hitsound": "0", "extras": "0:0:0:0:\n"}, {"x": "192", "y": "192", "time": "45100", "type": "1", "hitsound": "0", "extras": "0:0:0:0:\n"}, {"x": "320", "y": "192", "time": "45330", "type": "1", "hitsound": "0", "extras": "0:0:0:0:\n"}, {"x": "192", "y": "192", "time": "45561", "type": "1", "hitsound": "0", "extras": "0:0:0:0:\n"}, {"x": "64", "y": "192", "time": "45792", "type": "1", "hitsound": "0", "extras": "0:0:0:0:\n"}, {"x": "320", "y": "192", "time": "46023", "type": "1", "hitsound": "0", "extras": "0:0:0:0:\n"}, {"x": "192", "y": "192", "time": "46253", "type": "1", "hitsound": "0", "extras": "0:0:0:0:\n"}, {"x": "320", "y": "192", "time": "46484", "type": "1", "hitsound": "0", "extras": "0:0:0:0:\n"}, {"x": "448", "y": "192", "time": "46715", "type": "1", "hitsound": "0", "extras": "0:0:0:0:\n"}, {"x": "192", "y": "192", "time": "46946", "type": "1", "hitsound": "0", "extras": "0:0:0:0:\n"}, {"x": "320", "y": "192", "time": "47176", "type": "1", "hitsound": "0", "extras": "0:0:0:0:\n"}, {"x": "64", "y": "192", "time": "47407", "type": "1", "hitsound": "0", "extras": "0:0:0:0:\n"}, {"x": "192", "y": "192", "time": "47638", "type": "1", "hitsound": "0", "extras": "0:0:0:0:\n"}, {"x": "320", "y": "192", "time": "47869", "type": "1", "hitsound": "0", "extras": "0:0:0:0:\n"}, {"x": "448", "y": "192", "time": "48100", "type": "1", "hitsound": "0", "extras": "0:0:0:0:\n"}, {"x": "192", "y": "192", "time": "48330", "type": "1", "hitsound": "0", "extras": "0:0:0:0:\n"}, {"x": "64", "y": "192", "time": "48561", "type": "1", "hitsound": "0", "extras": "0:0:0:0:\n"}, {"x": "320", "y": "192", "time": "48792", "type": "1", "hitsound": "0", "extras": "0:0:0:0:\n"}, {"x": "192", "y": "192", "time": "49023", "type": "1", "hitsound": "0", "extras": "0:0:0:0:\n"}, {"x": "64", "y": "192", "time": "49253", "type": "1", "hitsound": "0", "extras": "0:0:0:0:\n"}, {"x": "192", "y": "192", "time": "49484", "type": "1", "hitsound": "0", "extras": "0:0:0:0:\n"}, {"x": "320", "y": "192", "time": "49715", "type": "1", "hitsound": "0", "extras": "0:0:0:0:\n"}, {"x": "448", "y": "192", "time": "49946", "type": "1", "hitsound": "0", "extras": "0:0:0:0:\n"}, {"x": "192", "y": "192", "time": "50176", "type": "1", "hitsound": "0", "extras": "0:0:0:0:\n"}, {"x": "64", "y": "192", "time": "50407", "type": "1", "hitsound": "0", "extras": "0:0:0:0:\n"}, {"x": "320", "y": "192", "time": "50638", "type": "1", "hitsound": "0", "extras": "0:0:0:0:\n"}, {"x": "448", "y": "192", "time": "50869", "type": "1", "hitsound": "0", "extras": "0:0:0:0:\n"}, {"x": "320", "y": "192", "time": "51100", "type": "1", "hitsound": "0", "extras": "0:0:0:0:\n"}, {"x": "192", "y": "192", "time": "51330", "type": "1", "hitsound": "0", "extras": "0:0:0:0:\n"}, {"x": "448", "y": "192", "time": "51561", "type": "1", "hitsound": "0", "extras": "0:0:0:0:\n"}, {"x": "64", "y": "192", "time": "51792", "type": "1", "hitsound": "2", "extras": "0:0:0:0:\n"}, {"x": "320", "y": "192", "time": "51792", "type": "1", "hitsound": "0", "extras": "0:0:0:0:\n"}, {"x": "64", "y": "192", "time": "52253", "type": "1", "hitsound": "2", "extras": "0:0:0:0:\n"}, {"x": "192", "y": "192", "time": "52715", "type": "1", "hitsound": "2", "extras": "0:0:0:0:\n"}, {"x": "320", "y": "192", "time": "52715", "type": "1", "hitsound": "0", "extras": "0:0:0:0:\n"}, {"x": "192", "y": "192", "time": "53176", "type": "1", "hitsound": "2", "extras": "0:0:0:0:\n"}, {"x": "320", "y": "192", "time": "53638", "type": "1", "hitsound": "2", "extras": "0:0:0:0:\n"}, {"x": "64", "y": "192", "time": "53638", "type": "1", "hitsound": "0", "extras": "0:0:0:0:\n"}, {"x": "320", "y": "192", "time": "54100", "type": "1", "hitsound": "2", "extras": "0:0:0:0:\n"}, {"x": "448", "y": "192", "time": "54561", "type": "1", "hitsound": "2", "extras": "0:0:0:0:\n"}, {"x": "64", "y": "192", "time": "54561", "type": "1", "hitsound": "0", "extras": "0:0:0:0:\n"}, {"x": "448", "y": "192", "time": "55023", "type": "1", "hitsound": "2", "extras": "0:0:0:0:\n"}, {"x": "64", "y": "192", "time": "55484", "type": "1", "hitsound": "2", "extras": "0:0:0:0:\n"}, {"x": "320", "y": "192", "time": "55484", "type": "1", "hitsound": "0", "extras": "0:0:0:0:\n"}, {"x": "192", "y": "192", "time": "55715", "type": "1", "hitsound": "2", "extras": "0:0:0:0:\n"}, {"x": "320", "y": "192", "time": "55946", "type": "1", "hitsound": "2", "extras": "0:0:0:0:\n"}, {"x": "448", "y": "192", "time": "55946", "type": "1", "hitsound": "0", "extras": "0:0:0:0:\n"}, {"x": "64", "y": "192", "time": "56176", "type": "1", "hitsound": "2", "extras": "0:0:0:0:\n"}, {"x": "320", "y": "192", "time": "56407", "type": "1", "hitsound": "2", "extras": "0:0:0:0:\n"}, {"x": "192", "y": "192", "time": "56407", "type": "1", "hitsound": "0", "extras": "0:0:0:0:\n"}, {"x": "448", "y": "192", "time": "56638", "type": "1", "hitsound": "2", "extras": "0:0:0:0:\n"}, {"x": "320", "y": "192", "time": "56869", "type": "1", "hitsound": "2", "extras": "0:0:0:0:\n"}, {"x": "64", "y": "192", "time": "56869", "type": "1", "hitsound": "0", "extras": "0:0:0:0:\n"}, {"x": "192", "y": "192", "time": "57100", "type": "1", "hitsound": "2", "extras": "0:0:0:0:\n"}, {"x": "448", "y": "192", "time": "57330", "type": "1", "hitsound": "0", "extras": "0:0:0:0:\n"}, {"x": "64", "y": "192", "time": "57330", "type": "1", "hitsound": "2", "extras": "0:0:0:0:\n"}, {"x": "320", "y": "192", "time": "57561", "type": "1", "hitsound": "2", "extras": "0:0:0:0:\n"}, {"x": "192", "y": "192", "time": "57792", "type": "1", "hitsound": "2", "extras": "0:0:0:0:\n"}, {"x": "448", "y": "192", "time": "57792", "type": "1", "hitsound": "0", "extras": "0:0:0:0:\n"}, {"x": "64", "y": "192", "time": "58023", "type": "1", "hitsound": "2", "extras": "0:0:0:0:\n"}, {"x": "320", "y": "192", "time": "58253", "type": "1", "hitsound": "2", "extras": "0:0:0:0:\n"}, {"x": "448", "y": "192", "time": "58253", "type": "1", "hitsound": "0", "extras": "0:0:0:0:\n"}, {"x": "64", "y": "192", "time": "58369", "type": "1", "hitsound": "2", "extras": "0:0:0:0:\n"}, {"x": "448", "y": "192", "time": "58484", "type": "1", "hitsound": "2", "extras": "0:0:0:0:\n"}, {"x": "64", "y": "192", "time": "58600", "type": "1", "hitsound": "2", "extras": "0:0:0:0:\n"}, {"x": "320", "y": "192", "time": "58715", "type": "128", "hitsound": "2", "extras": "59176:0:0:0:0:\n"}, {"x": "192", "y": "192", "time": "58715", "type": "1", "hitsound": "0", "extras": "0:0:0:0:\n"}, {"x": "64", "y": "192", "time": "59176", "type": "1", "hitsound": "4", "extras": "0:0:0:0:\n"}, {"x": "448", "y": "192", "time": "59176", "type": "1", "hitsound": "0", "extras": "0:0:0:0:\n"}, {"x": "192", "y": "192", "time": "59292", "type": "1", "hitsound": "0", "extras": "0:0:0:0:\n"}, {"x": "320", "y": "192", "time": "59407", "type": "1", "hitsound": "0", "extras": "0:0:0:0:\n"}, {"x": "448", "y": "192", "time": "59523", "type": "1", "hitsound": "0", "extras": "0:0:0:0:\n"}, {"x": "64", "y": "192", "time": "59638", "type": "1", "hitsound": "2", "extras": "0:0:0:0:\n"}, {"x": "192", "y": "192", "time": "59753", "type": "1", "hitsound": "0", "extras": "0:0:0:0:\n"}, {"x": "320", "y": "192", "time": "59869", "type": "1", "hitsound": "0", "extras": "0:0:0:0:\n"}, {"x": "448", "y": "192", "time": "59984", "type": "1", "hitsound": "0", "extras": "0:0:0:0:\n"}, {"x": "192", "y": "192", "time": "60100", "type": "1", "hitsound": "4", "extras": "0:0:0:0:\n"}, {"x": "64", "y": "192", "time": "60215", "type": "1", "hitsound": "0", "extras": "0:0:0:0:\n"}, {"x": "320", "y": "192", "time": "60330", "type": "1", "hitsound": "0", "extras": "0:0:0:0:\n"}, {"x": "192", "y": "192", "time": "60446", "type": "1", "hitsound": "0", "extras": "0:0:0:0:\n"}, {"x": "448", "y": "192", "time": "60561", "type": "1", "hitsound": "2", "extras": "0:0:0:0:\n"}, {"x": "320", "y": "192", "time": "60676", "type": "1", "hitsound": "0", "extras": "0:0:0:0:\n"}, {"x": "192", "y": "192", "time": "60792", "type": "1", "hitsound": "0", "extras": "0:0:0:0:\n"}, {"x": "64", "y": "192", "time": "60907", "type": "1", "hitsound": "0", "extras": "0:0:0:0:\n"}, {"x": "320", "y": "192", "time": "61023", "type": "1", "hitsound": "4", "extras": "0:0:0:0:\n"}, {"x": "192", "y": "192", "time": "61138", "type": "1", "hitsound": "0", "extras": "0:0:0:0:\n"}, {"x": "64", "y": "192", "time": "61253", "type": "1", "hitsound": "0", "extras": "0:0:0:0:\n"}, {"x": "192", "y": "192", "time": "61369", "type": "1", "hitsound": "0", "extras": "0:0:0:0:\n"}, {"x": "448", "y": "192", "time": "61484", "type": "1", "hitsound": "2", "extras": "0:0:0:0:\n"}, {"x": "320", "y": "192", "time": "61600", "type": "1", "hitsound": "0", "extras": "0:0:0:0:\n"}, {"x": "64", "y": "192", "time": "61715", "type": "1", "hitsound": "0", "extras": "0:0:0:0:\n"}, {"x": "192", "y": "192", "time": "61830", "type": "1", "hitsound": "0", "extras": "0:0:0:0:\n"}, {"x": "448", "y": "192", "time": "61946", "type": "1", "hitsound": "4", "extras": "0:0:0:0:\n"}, {"x": "320", "y": "192", "time": "62061", "type": "1", "hitsound": "0", "extras": "0:0:0:0:\n"}, {"x": "192", "y": "192", "time": "62176", "type": "1", "hitsound": "0", "extras": "0:0:0:0:\n"}, {"x": "320", "y": "192", "time": "62292", "type": "1", "hitsound": "0", "extras": "0:0:0:0:\n"}, {"x": "64", "y": "192", "time": "62407", "type": "1", "hitsound": "2", "extras": "0:0:0:0:\n"}, {"x": "192", "y": "192", "time": "62523", "type": "1", "hitsound": "0", "extras": "0:0:0:0:\n"}, {"x": "448", "y": "192", "time": "62638", "type": "1", "hitsound": "0", "extras": "0:0:0:0:\n"}, {"x": "320", "y": "192", "time": "62753", "type": "1", "hitsound": "0", "extras": "0:0:0:0:\n"}, {"x": "64", "y": "192", "time": "62869", "type": "1", "hitsound": "4", "extras": "0:0:0:0:\n"}, {"x": "448", "y": "192", "time": "62984", "type": "1", "hitsound": "0", "extras": "0:0:0:0:\n"}, {"x": "192", "y": "192", "time": "63100", "type": "1", "hitsound": "0", "extras": "0:0:0:0:\n"}, {"x": "320", "y": "192", "time": "63215", "type": "1", "hitsound": "0", "extras": "0:0:0:0:\n"}, {"x": "64", "y": "192", "time": "63330", "type": "1", "hitsound": "2", "extras": "0:0:0:0:\n"}, {"x": "448", "y": "192", "time": "63446", "type": "1", "hitsound": "0", "extras": "0:0:0:0:\n"}, {"x": "192", "y": "192", "time": "63561", "type": "1", "hitsound": "0", "extras": "0:0:0:0:\n"}, {"x": "64", "y": "192", "time": "63676", "type": "1", "hitsound": "0", "extras": "0:0:0:0:\n"}, {"x": "320", "y": "192", "time": "63792", "type": "1", "hitsound": "4", "extras": "0:0:0:0:\n"}, {"x": "192", "y": "192", "time": "63907", "type": "1", "hitsound": "0", "extras": "0:0:0:0:\n"}, {"x": "320", "y": "192", "time": "64023", "type": "1", "hitsound": "0", "extras": "0:0:0:0:\n"}, {"x": "448", "y": "192", "time": "64138", "type": "1", "hitsound": "0", "extras": "0:0:0:0:\n"}, {"x": "192", "y": "192", "time": "64253", "type": "1", "hitsound": "2", "extras": "0:0:0:0:\n"}, {"x": "320", "y": "192", "time": "64369", "type": "1", "hitsound": "0", "extras": "0:0:0:0:\n"}, {"x": "192", "y": "192", "time": "64484", "type": "1", "hitsound": "0", "extras": "0:0:0:0:\n"}, {"x": "64", "y": "192", "time": "64600", "type": "1", "hitsound": "0", "extras": "0:0:0:0:\n"}, {"x": "448", "y": "192", "time": "64715", "type": "1", "hitsound": "4", "extras": "0:0:0:0:\n"}, {"x": "192", "y": "192", "time": "64830", "type": "1", "hitsound": "0", "extras": "0:0:0:0:\n"}, {"x": "320", "y": "192", "time": "64946", "type": "1", "hitsound": "0", "extras": "0:0:0:0:\n"}, {"x": "64", "y": "192", "time": "65061", "type": "1", "hitsound": "0", "extras": "0:0:0:0:\n"}, {"x": "192", "y": "192", "time": "65176", "type": "1", "hitsound": "2", "extras": "0:0:0:0:\n"}, {"x": "448", "y": "192", "time": "65292", "type": "1", "hitsound": "0", "extras": "0:0:0:0:\n"}, {"x": "320", "y": "192", "time": "65407", "type": "1", "hitsound": "0", "extras": "0:0:0:0:\n"}, {"x": "64", "y": "192", "time": "65523", "type": "1", "hitsound": "0", "extras": "0:0:0:0:\n"}, {"x": "320", "y": "192", "time": "65638", "type": "128", "hitsound": "4", "extras": "65869:0:0:0:0:\n"}, {"x": "192", "y": "192", "time": "65869", "type": "128", "hitsound": "0", "extras": "66100:0:0:0:0:\n"}, {"x": "448", "y": "192", "time": "66100", "type": "128", "hitsound": "2", "extras": "66330:0:0:0:0:\n"}, {"x": "64", "y": "192", "time": "66330", "type": "128", "hitsound": "4", "extras": "66561:0:0:0:0:\n"}, {"x": "448", "y": "192", "time": "66561", "type": "1", "hitsound": "4", "extras": "0:0:0:0:\n"}, {"x": "320", "y": "192", "time": "66676", "type": "1", "hitsound": "0", "extras": "0:0:0:0:\n"}, {"x": "192", "y": "192", "time": "66792", "type": "1", "hitsound": "0", "extras": "0:0:0:0:\n"}, {"x": "448", "y": "192", "time": "66907", "type": "1", "hitsound": "0", "extras": "0:0:0:0:\n"}, {"x": "64", "y": "192", "time": "67023", "type": "1", "hitsound": "2", "extras": "0:0:0:0:\n"}, {"x": "320", "y": "192", "time": "67138", "type": "1", "hitsound": "0", "extras": "0:0:0:0:\n"}, {"x": "192", "y": "192", "time": "67253", "type": "1", "hitsound": "0", "extras": "0:0:0:0:\n"}, {"x": "64", "y": "192", "time": "67369", "type": "1", "hitsound": "0", "extras": "0:0:0:0:\n"}, {"x": "320", "y": "192", "time": "67484", "type": "1", "hitsound": "4", "extras": "0:0:0:0:\n"}, {"x": "192", "y": "192", "time": "67600", "type": "1", "hitsound": "0", "extras": "0:0:0:0:\n"}, {"x": "448", "y": "192", "time": "67715", "type": "1", "hitsound": "0", "extras": "0:0:0:0:\n"}, {"x": "64", "y": "192", "time": "67830", "type": "1", "hitsound": "0", "extras": "0:0:0:0:\n"}, {"x": "192", "y": "192", "time": "67946", "type": "1", "hitsound": "2", "extras": "0:0:0:0:\n"}, {"x": "320", "y": "192", "time": "68061", "type": "1", "hitsound": "0", "extras": "0:0:0:0:\n"}, {"x": "64", "y": "192", "time": "68176", "type": "1", "hitsound": "0", "extras": "0:0:0:0:\n"}, {"x": "448", "y": "192", "time": "68292", "type": "1", "hitsound": "0", "extras": "0:0:0:0:\n"}, {"x": "320", "y": "192", "time": "68407", "type": "1", "hitsound": "4", "extras": "0:0:0:0:\n"}, {"x": "192", "y": "192", "time": "68523", "type": "1", "hitsound": "0", "extras": "0:0:0:0:\n"}, {"x": "448", "y": "192", "time": "68638", "type": "1", "hitsound": "0", "extras": "0:0:0:0:\n"}, {"x": "64", "y": "192", "time": "68753", "type": "1", "hitsound": "0", "extras": "0:0:0:0:\n"}, {"x": "320", "y": "192", "time": "68869", "type": "1", "hitsound": "2", "extras": "0:0:0:0:\n"}, {"x": "192", "y": "192", "time": "68984", "type": "1", "hitsound": "0", "extras": "0:0:0:0:\n"}, {"x": "448", "y": "192", "time": "69100", "type": "1", "hitsound": "0", "extras": "0:0:0:0:\n"}, {"x": "64", "y": "192", "time": "69215", "type": "1", "hitsound": "0", "extras": "0:0:0:0:\n"}, {"x": "320", "y": "192", "time": "69330", "type": "1", "hitsound": "4", "extras": "0:0:0:0:\n"}, {"x": "448", "y": "192", "time": "69446", "type": "1", "hitsound": "0", "extras": "0:0:0:0:\n"}, {"x": "320", "y": "192", "time": "69561", "type": "1", "hitsound": "0", "extras": "0:0:0:0:\n"}, {"x": "192", "y": "192", "time": "69676", "type": "1", "hitsound": "0", "extras": "0:0:0:0:\n"}, {"x": "64", "y": "192", "time": "69792", "type": "1", "hitsound": "2", "extras": "0:0:0:0:\n"}, {"x": "192", "y": "192", "time": "69907", "type": "1", "hitsound": "0", "extras": "0:0:0:0:\n"}, {"x": "320", "y": "192", "time": "70023", "type": "1", "hitsound": "0", "extras": "0:0:0:0:\n"}, {"x": "448", "y": "192", "time": "70138", "type": "1", "hitsound": "0", "extras": "0:0:0:0:\n"}, {"x": "64", "y": "192", "time": "70253", "type": "1", "hitsound": "4", "extras": "0:0:0:0:\n"}, {"x": "192", "y": "192", "time": "70369", "type": "1", "hitsound": "0", "extras": "0:0:0:0:\n"}, {"x": "448", "y": "192", "time": "70484", "type": "1", "hitsound": "0", "extras": "0:0:0:0:\n"}, {"x": "64", "y": "192", "time": "70600", "type": "1", "hitsound": "0", "extras": "0:0:0:0:\n"}, {"x": "320", "y": "192", "time": "70715", "type": "1", "hitsound": "2", "extras": "0:0:0:0:\n"}, {"x": "448", "y": "192", "time": "70830", "type": "1", "hitsound": "0", "extras": "0:0:0:0:\n"}, {"x": "320", "y": "192", "time": "70946", "type": "1", "hitsound": "0", "extras": "0:0:0:0:\n"}, {"x": "192", "y": "192", "time": "71061", "type": "1", "hitsound": "0", "extras": "0:0:0:0:\n"}, {"x": "448", "y": "192", "time": "71176", "type": "1", "hitsound": "4", "extras": "0:0:0:0:\n"}, {"x": "64", "y": "192", "time": "71292", "type": "1", "hitsound": "0", "extras": "0:0:0:0:\n"}, {"x": "192", "y": "192", "time": "71407", "type": "1", "hitsound": "0", "extras": "0:0:0:0:\n"}, {"x": "448", "y": "192", "time": "71523", "type": "1", "hitsound": "0", "extras": "0:0:0:0:\n"}, {"x": "320", "y": "192", "time": "71638", "type": "1", "hitsound": "2", "extras": "0:0:0:0:\n"}, {"x": "192", "y": "192", "time": "71753", "type": "1", "hitsound": "0", "extras": "0:0:0:0:\n"}, {"x": "64", "y": "192", "time": "71869", "type": "1", "hitsound": "0", "extras": "0:0:0:0:\n"}, {"x": "192", "y": "192", "time": "71984", "type": "1", "hitsound": "0", "extras": "0:0:0:0:\n"}, {"x": "320", "y": "192", "time": "72100", "type": "1", "hitsound": "4", "extras": "0:0:0:0:\n"}, {"x": "448", "y": "192", "time": "72215", "type": "1", "hitsound": "0", "extras": "0:0:0:0:\n"}, {"x": "192", "y": "192", "time": "72330", "type": "1", "hitsound": "0", "extras": "0:0:0:0:\n"}, {"x": "320", "y": "192", "time": "72446", "type": "1", "hitsound": "0", "extras": "0:0:0:0:\n"}, {"x": "64", "y": "192", "time": "72561", "type": "1", "hitsound": "2", "extras": "0:0:0:0:\n"}, {"x": "320", "y": "192", "time": "72676", "type": "1", "hitsound": "0", "extras": "0:0:0:0:\n"}, {"x": "192", "y": "192", "time": "72792", "type": "1", "hitsound": "0", "extras": "0:0:0:0:\n"}, {"x": "448", "y": "192", "time": "72907", "type": "1", "hitsound": "0", "extras": "0:0:0:0:\n"}, {"x": "320", "y": "192", "time": "73023", "type": "1", "hitsound": "0", "extras": "0:0:0:0:\n"}, {"x": "64", "y": "192", "time": "73138", "type": "1", "hitsound": "0", "extras": "0:0:0:0:\n"}, {"x": "448", "y": "192", "time": "73253", "type": "1", "hitsound": "0", "extras": "0:0:0:0:\n"}, {"x": "192", "y": "192", "time": "73369", "type": "1", "hitsound": "0", "extras": "0:0:0:0:\n"}, {"x": "64", "y": "192", "time": "73484", "type": "1", "hitsound": "0", "extras": "0:0:0:0:\n"}, {"x": "192", "y": "192", "time": "73600", "type": "1", "hitsound": "0", "extras": "0:0:0:0:\n"}, {"x": "320", "y": "192", "time": "73715", "type": "1", "hitsound": "0", "extras": "0:0:0:0:\n"}, {"x": "448", "y": "192", "time": "73830", "type": "1", "hitsound": "0", "extras": "0:0:0:0:\n"}, {"x": "320", "y": "192", "time": "73946", "type": "1", "hitsound": "4", "extras": "0:0:0:0:\n"}, {"x": "64", "y": "192", "time": "74176", "type": "1", "hitsound": "4", "extras": "0:0:0:0:\n"}, {"x": "192", "y": "192", "time": "74407", "type": "1", "hitsound": "4", "extras": "0:0:0:0:\n"}, {"x": "64", "y": "192", "time": "74638", "type": "1", "hitsound": "4", "extras": "0:0:0:0:\n"}, {"x": "448", "y": "192", "time": "74869", "type": "1", "hitsound": "4", "extras": "0:0:0:0:\n"}, {"x": "192", "y": "192", "time": "74984", "type": "1", "hitsound": "0", "extras": "0:0:0:0:\n"}, {"x": "320", "y": "192", "time": "75100", "type": "1", "hitsound": "0", "extras": "0:0:0:0:\n"}, {"x": "64", "y": "192", "time": "75215", "type": "1", "hitsound": "0", "extras": "0:0:0:0:\n"}, {"x": "192", "y": "192", "time": "75330", "type": "1", "hitsound": "4", "extras": "0:0:0:0:\n"}, {"x": "448", "y": "192", "time": "75561", "type": "1", "hitsound": "4", "extras": "0:0:0:0:\n"}, {"x": "320", "y": "192", "time": "75792", "type": "1", "hitsound": "4", "extras": "0:0:0:0:\n"}, {"x": "64", "y": "192", "time": "76023", "type": "1", "hitsound": "4", "extras": "0:0:0:0:\n"}, {"x": "192", "y": "192", "time": "76253", "type": "1", "hitsound": "4", "extras": "0:0:0:0:\n"}, {"x": "320", "y": "192", "time": "76369", "type": "1", "hitsound": "0", "extras": "0:0:0:0:\n"}, {"x": "448", "y": "192", "time": "76484", "type": "1", "hitsound": "0", "extras": "0:0:0:0:\n"}, {"x": "64", "y": "192", "time": "76600", "type": "1", "hitsound": "0", "extras": "0:0:0:0:\n"}, {"x": "192", "y": "192", "time": "76715", "type": "1", "hitsound": "4", "extras": "0:0:0:0:\n"}, {"x": "320", "y": "192", "time": "76946", "type": "1", "hitsound": "4", "extras": "0:0:0:0:\n"}, {"x": "192", "y": "192", "time": "77176", "type": "1", "hitsound": "4", "extras": "0:0:0:0:\n"}, {"x": "448", "y": "192", "time": "77407", "type": "1", "hitsound": "4", "extras": "0:0:0:0:\n"}, {"x": "64", "y": "192", "time": "77638", "type": "1", "hitsound": "4", "extras": "0:0:0:0:\n"}, {"x": "320", "y": "192", "time": "77869", "type": "1", "hitsound": "4", "extras": "0:0:0:0:\n"}, {"x": "192", "y": "192", "time": "78100", "type": "1", "hitsound": "4", "extras": "0:0:0:0:\n"}, {"x": "448", "y": "192", "time": "78330", "type": "1", "hitsound": "4", "extras": "0:0:0:0:\n"}, {"x": "192", "y": "192", "time": "78561", "type": "1", "hitsound": "4", "extras": "0:0:0:0:\n"}, {"x": "320", "y": "192", "time": "78792", "type": "1", "hitsound": "4", "extras": "0:0:0:0:\n"}, {"x": "448", "y": "192", "time": "79023", "type": "1", "hitsound": "4", "extras": "0:0:0:0:\n"}, {"x": "192", "y": "192", "time": "79138", "type": "1", "hitsound": "0", "extras": "0:0:0:0:\n"}, {"x": "64", "y": "192", "time": "79253", "type": "1", "hitsound": "4", "extras": "0:0:0:0:\n"}, {"x": "320", "y": "192", "time": "79484", "type": "1", "hitsound": "4", "extras": "0:0:0:0:\n"}, {"x": "192", "y": "192", "time": "79715", "type": "1", "hitsound": "4", "extras": "0:0:0:0:\n"}, {"x": "448", "y": "192", "time": "79946", "type": "1", "hitsound": "4", "extras": "0:0:0:0:\n"}, {"x": "64", "y": "192", "time": "80176", "type": "1", "hitsound": "4", "extras": "0:0:0:0:\n"}, {"x": "192", "y": "192", "time": "80407", "type": "1", "hitsound": "4", "extras": "0:0:0:0:\n"}, {"x": "320", "y": "192", "time": "80638", "type": "1", "hitsound": "4", "extras": "0:0:0:0:\n"}, {"x": "448", "y": "192", "time": "80869", "type": "1", "hitsound": "4", "extras": "0:0:0:0:\n"}, {"x": "320", "y": "192", "time": "81100", "type": "1", "hitsound": "4", "extras": "0:0:0:0:\n"}, {"x": "64", "y": "192", "time": "81330", "type": "1", "hitsound": "4", "extras": "0:0:0:0:\n"}, {"x": "192", "y": "192", "time": "81561", "type": "1", "hitsound": "4", "extras": "0:0:0:0:\n"}, {"x": "448", "y": "192", "time": "81792", "type": "1", "hitsound": "4", "extras": "0:0:0:0:\n"}, {"x": "320", "y": "192", "time": "82023", "type": "1", "hitsound": "4", "extras": "0:0:0:0:\n"}, {"x": "64", "y": "192", "time": "82253", "type": "1", "hitsound": "4", "extras": "0:0:0:0:\n"}, {"x": "192", "y": "192", "time": "82369", "type": "1", "hitsound": "0", "extras": "0:0:0:0:\n"}, {"x": "448", "y": "192", "time": "82484", "type": "1", "hitsound": "0", "extras": "0:0:0:0:\n"}, {"x": "320", "y": "192", "time": "82600", "type": "1", "hitsound": "0", "extras": "0:0:0:0:\n"}, {"x": "192", "y": "192", "time": "82715", "type": "1", "hitsound": "4", "extras": "0:0:0:0:\n"}, {"x": "448", "y": "192", "time": "82946", "type": "1", "hitsound": "4", "extras": "0:0:0:0:\n"}, {"x": "320", "y": "192", "time": "83176", "type": "1", "hitsound": "4", "extras": "0:0:0:0:\n"}, {"x": "64", "y": "192", "time": "83407", "type": "1", "hitsound": "4", "extras": "0:0:0:0:\n"}, {"x": "320", "y": "192", "time": "83638", "type": "1", "hitsound": "4", "extras": "0:0:0:0:\n"}, {"x": "448", "y": "192", "time": "83753", "type": "1", "hitsound": "0", "extras": "0:0:0:0:\n"}, {"x": "320", "y": "192", "time": "83869", "type": "1", "hitsound": "0", "extras": "0:0:0:0:\n"}, {"x": "192", "y": "192", "time": "83984", "type": "1", "hitsound": "0", "extras": "0:0:0:0:\n"}, {"x": "448", "y": "192", "time": "84100", "type": "1", "hitsound": "4", "extras": "0:0:0:0:\n"}, {"x": "64", "y": "192", "time": "84330", "type": "1", "hitsound": "4", "extras": "0:0:0:0:\n"}, {"x": "448", "y": "192", "time": "84561", "type": "1", "hitsound": "4", "extras": "0:0:0:0:\n"}, {"x": "320", "y": "192", "time": "84792", "type": "1", "hitsound": "4", "extras": "0:0:0:0:\n"}, {"x": "64", "y": "192", "time": "85023", "type": "1", "hitsound": "4", "extras": "0:0:0:0:\n"}, {"x": "192", "y": "192", "time": "85253", "type": "1", "hitsound": "4", "extras": "0:0:0:0:\n"}, {"x": "320", "y": "192", "time": "85484", "type": "1", "hitsound": "0", "extras": "0:0:0:0:\n"}, {"x": "448", "y": "192", "time": "85484", "type": "1", "hitsound": "2", "extras": "0:0:0:0:\n"}, {"x": "192", "y": "192", "time": "85715", "type": "1", "hitsound": "4", "extras": "0:0:0:0:\n"}, {"x": "64", "y": "192", "time": "85946", "type": "1", "hitsound": "4", "extras": "0:0:0:0:\n"}, {"x": "448", "y": "192", "time": "86176", "type": "1", "hitsound": "4", "extras": "0:0:0:0:\n"}, {"x": "320", "y": "192", "time": "86407", "type": "1", "hitsound": "0", "extras": "0:0:0:0:\n"}, {"x": "192", "y": "192", "time": "86407", "type": "1", "hitsound": "2", "extras": "0:0:0:0:\n"}, {"x": "64", "y": "192", "time": "86638", "type": "1", "hitsound": "4", "extras": "0:0:0:0:\n"}, {"x": "448", "y": "192", "time": "86869", "type": "1", "hitsound": "4", "extras": "0:0:0:0:\n"}, {"x": "320", "y": "192", "time": "86984", "type": "1", "hitsound": "4", "extras": "0:0:0:0:\n"}, {"x": "64", "y": "192", "time": "87100", "type": "1", "hitsound": "4", "extras": "0:0:0:0:\n"}, {"x": "192", "y": "192", "time": "87215", "type": "1", "hitsound": "4", "extras": "0:0:0:0:\n"}, {"x": "448", "y": "192", "time": "87330", "type": "1", "hitsound": "2", "extras": "0:0:0:0:\n"}, {"x": "320", "y": "192", "time": "87446", "type": "1", "hitsound": "4", "extras": "0:0:0:0:\n"}, {"x": "64", "y": "192", "time": "87561", "type": "1", "hitsound": "4", "extras": "0:0:0:0:\n"}, {"x": "192", "y": "192", "time": "87676", "type": "1", "hitsound": "4", "extras": "0:0:0:0:\n"}, {"x": "448", "y": "192", "time": "87792", "type": "1", "hitsound": "4", "extras": "0:0:0:0:\n"}, {"x": "320", "y": "192", "time": "88023", "type": "1", "hitsound": "0", "extras": "0:0:0:0:\n"}, {"x": "192", "y": "192", "time": "88253", "type": "1", "hitsound": "0", "extras": "0:0:0:0:\n"}, {"x": "64", "y": "192", "time": "88484", "type": "1", "hitsound": "0", "extras": "0:0:0:0:\n"}, {"x": "448", "y": "192", "time": "88715", "type": "1", "hitsound": "0", "extras": "0:0:0:0:\n"}, {"x": "320", "y": "192", "time": "88715", "type": "1", "hitsound": "2", "extras": "0:0:0:0:\n"}, {"x": "64", "y": "192", "time": "89176", "type": "1", "hitsound": "2", "extras": "0:0:0:0:\n"}, {"x": "320", "y": "192", "time": "89638", "type": "1", "hitsound": "2", "extras": "0:0:0:0:\n"}, {"x": "192", "y": "192", "time": "90100", "type": "1", "hitsound": "2", "extras": "0:0:0:0:\n"}, {"x": "448", "y": "192", "time": "90561", "type": "1", "hitsound": "2", "extras": "0:0:0:0:\n"}, {"x": "64", "y": "192", "time": "91023", "type": "1", "hitsound": "2", "extras": "0:0:0:0:\n"}, {"x": "320", "y": "192", "time": "91484", "type": "1", "hitsound": "2", "extras": "0:0:0:0:\n"}, {"x": "192", "y": "192", "time": "91946", "type": "1", "hitsound": "2", "extras": "0:0:0:0:\n"}, {"x": "448", "y": "192", "time": "92407", "type": "1", "hitsound": "2", "extras": "0:0:0:0:\n"}, {"x": "64", "y": "192", "time": "92638", "type": "1", "hitsound": "2", "extras": "0:0:0:0:\n"}, {"x": "320", "y": "192", "time": "92869", "type": "1", "hitsound": "2", "extras": "0:0:0:0:\n"}, {"x": "192", "y": "192", "time": "93100", "type": "1", "hitsound": "2", "extras": "0:0:0:0:\n"}, {"x": "448", "y": "192", "time": "93330", "type": "1", "hitsound": "2", "extras": "0:0:0:0:\n"}, {"x": "64", "y": "192", "time": "93561", "type": "1", "hitsound": "2", "extras": "0:0:0:0:\n"}, {"x": "320", "y": "192", "time": "93792", "type": "1", "hitsound": "2", "extras": "0:0:0:0:\n"}, {"x": "192", "y": "192", "time": "94023", "type": "1", "hitsound": "2", "extras": "0:0:0:0:\n"}, {"x": "448", "y": "192", "time": "94253", "type": "1", "hitsound": "2", "extras": "0:0:0:0:\n"}, {"x": "64", "y": "192", "time": "94369", "type": "1", "hitsound": "2", "extras": "0:0:0:0:\n"}, {"x": "320", "y": "192", "time": "94484", "type": "1", "hitsound": "2", "extras": "0:0:0:0:\n"}, {"x": "192", "y": "192", "time": "94600", "type": "1", "hitsound": "2", "extras": "0:0:0:0:\n"}, {"x": "448", "y": "192", "time": "94715", "type": "1", "hitsound": "2", "extras": "0:0:0:0:\n"}, {"x": "64", "y": "192", "time": "94830", "type": "1", "hitsound": "2", "extras": "0:0:0:0:\n"}, {"x": "320", "y": "192", "time": "94946", "type": "1", "hitsound": "2", "extras": "0:0:0:0:\n"}, {"x": "192", "y": "192", "time": "95061", "type": "1", "hitsound": "2", "extras": "0:0:0:0:\n"}, {"x": "448", "y": "192", "time": "95176", "type": "1", "hitsound": "2", "extras": "0:0:0:0:\n"}, {"x": "64", "y": "192", "time": "95292", "type": "1", "hitsound": "2", "extras": "0:0:0:0:\n"}, {"x": "320", "y": "192", "time": "95407", "type": "1", "hitsound": "2", "extras": "0:0:0:0:\n"}, {"x": "192", "y": "192", "time": "95523", "type": "1", "hitsound": "2", "extras": "0:0:0:0:\n"}, {"x": "448", "y": "192", "time": "95638", "type": "128", "hitsound": "2", "extras": "96100:0:0:0:0:\n"}, {"x": "320", "y": "192", "time": "96100", "type": "128", "hitsound": "4", "extras": "96330:0:0:0:0:\n"}, {"x": "64", "y": "192", "time": "96100", "type": "1", "hitsound": "2", "extras": "0:0:0:0:\n"}, {"x": "192", "y": "192", "time": "96330", "type": "128", "hitsound": "0", "extras": "96561:0:0:0:0:\n"}, {"x": "64", "y": "192", "time": "96561", "type": "1", "hitsound": "2", "extras": "0:0:0:0:\n"}, {"x": "320", "y": "192", "time": "96676", "type": "1", "hitsound": "0", "extras": "0:0:0:0:\n"}, {"x": "448", "y": "192", "time": "96792", "type": "1", "hitsound": "0", "extras": "0:0:0:0:\n"}, {"x": "64", "y": "192", "time": "96907", "type": "1", "hitsound": "0", "extras": "0:0:0:0:\n"}, {"x": "192", "y": "192", "time": "97023", "type": "128", "hitsound": "4", "extras": "97253:0:0:0:0:\n"}, {"x": "448", "y": "192", "time": "97253", "type": "128", "hitsound": "0", "extras": "97484:0:0:0:0:\n"}, {"x": "64", "y": "192", "time": "97484", "type": "128", "hitsound": "2", "extras": "97715:0:0:0:0:\n"}, {"x": "192", "y": "192", "time": "97715", "type": "128", "hitsound": "0", "extras": "97946:0:0:0:0:\n"}, {"x": "64", "y": "192", "time": "97946", "type": "1", "hitsound": "4", "extras": "0:0:0:0:\n"}, {"x": "448", "y": "192", "time": "98061", "type": "1", "hitsound": "0", "extras": "0:0:0:0:\n"}, {"x": "320", "y": "192", "time": "98176", "type": "1", "hitsound": "0", "extras": "0:0:0:0:\n"}, {"x": "192", "y": "192", "time": "98292", "type": "1", "hitsound": "0", "extras": "0:0:0:0:\n"}, {"x": "64", "y": "192", "time": "98407", "type": "1", "hitsound": "2", "extras": "0:0:0:0:\n"}, {"x": "448", "y": "192", "time": "98523", "type": "1", "hitsound": "0", "extras": "0:0:0:0:\n"}, {"x": "192", "y": "192", "time": "98638", "type": "1", "hitsound": "0", "extras": "0:0:0:0:\n"}, {"x": "320", "y": "192", "time": "98753", "type": "1", "hitsound": "0", "extras": "0:0:0:0:\n"}, {"x": "64", "y": "192", "time": "98869", "type": "128", "hitsound": "4", "extras": "99100:0:0:0:0:\n"}, {"x": "448", "y": "192", "time": "99100", "type": "128", "hitsound": "0", "extras": "99330:0:0:0:0:\n"}, {"x": "192", "y": "192", "time": "99330", "type": "128", "hitsound": "2", "extras": "99561:0:0:0:0:\n"}, {"x": "320", "y": "192", "time": "99561", "type": "128", "hitsound": "0", "extras": "99792:0:0:0:0:\n"}, {"x": "64", "y": "192", "time": "99792", "type": "128", "hitsound": "4", "extras": "100023:0:0:0:0:\n"}, {"x": "448", "y": "192", "time": "100023", "type": "128", "hitsound": "0", "extras": "100253:0:0:0:0:\n"}, {"x": "192", "y": "192", "time": "100253", "type": "1", "hitsound": "2", "extras": "0:0:0:0:\n"}, {"x": "64", "y": "192", "time": "100369", "type": "1", "hitsound": "0", "extras": "0:0:0:0:\n"}, {"x": "320", "y": "192", "time": "100484", "type": "1", "hitsound": "0", "extras": "0:0:0:0:\n"}, {"x": "192", "y": "192", "time": "100600", "type": "1", "hitsound": "0", "extras": "0:0:0:0:\n"}, {"x": "64", "y": "192", "time": "100715", "type": "128", "hitsound": "4", "extras": "100946:0:0:0:0:\n"}, {"x": "448", "y": "192", "time": "100946", "type": "128", "hitsound": "0", "extras": "101176:0:0:0:0:\n"}, {"x": "320", "y": "192", "time": "101176", "type": "128", "hitsound": "2", "extras": "101407:0:0:0:0:\n"}, {"x": "192", "y": "192", "time": "101407", "type": "128", "hitsound": "0", "extras": "101638:0:0:0:0:\n"}, {"x": "320", "y": "192", "time": "101638", "type": "1", "hitsound": "4", "extras": "0:0:0:0:\n"}, {"x": "448", "y": "192", "time": "101753", "type": "1", "hitsound": "0", "extras": "0:0:0:0:\n"}, {"x": "64", "y": "192", "time": "101869", "type": "1", "hitsound": "0", "extras": "0:0:0:0:\n"}, {"x": "192", "y": "192", "time": "101984", "type": "1", "hitsound": "0", "extras": "0:0:0:0:\n"}, {"x": "448", "y": "192", "time": "102100", "type": "1", "hitsound": "2", "extras": "0:0:0:0:\n"}, {"x": "320", "y": "192", "time": "102215", "type": "1", "hitsound": "0", "extras": "0:0:0:0:\n"}, {"x": "64", "y": "192", "time": "102330", "type": "1", "hitsound": "0", "extras": "0:0:0:0:\n"}, {"x": "192", "y": "192", "time": "102446", "type": "1", "hitsound": "0", "extras": "0:0:0:0:\n"}, {"x": "448", "y": "192", "time": "102561", "type": "1", "hitsound": "4", "extras": "0:0:0:0:\n"}, {"x": "320", "y": "192", "time": "102676", "type": "1", "hitsound": "0", "extras": "0:0:0:0:\n"}, {"x": "192", "y": "192", "time": "102792", "type": "1", "hitsound": "0", "extras": "0:0:0:0:\n"}, {"x": "448", "y": "192", "time": "102907", "type": "1", "hitsound": "0", "extras": "0:0:0:0:\n"}, {"x": "64", "y": "192", "time": "103023", "type": "1", "hitsound": "2", "extras": "0:0:0:0:\n"}, {"x": "192", "y": "192", "time": "103138", "type": "1", "hitsound": "0", "extras": "0:0:0:0:\n"}, {"x": "320", "y": "192", "time": "103253", "type": "1", "hitsound": "0", "extras": "0:0:0:0:\n"}, {"x": "448", "y": "192", "time": "103369", "type": "1", "hitsound": "0", "extras": "0:0:0:0:\n"}, {"x": "64", "y": "192", "time": "103484", "type": "128", "hitsound": "4", "extras": "103715:0:0:0:0:\n"}, {"x": "448", "y": "192", "time": "103715", "type": "128", "hitsound": "0", "extras": "103946:0:0:0:0:\n"}, {"x": "320", "y": "192", "time": "103946", "type": "1", "hitsound": "2", "extras": "0:0:0:0:\n"}, {"x": "192", "y": "192", "time": "104061", "type": "1", "hitsound": "0", "extras": "0:0:0:0:\n"}, {"x": "64", "y": "192", "time": "104176", "type": "1", "hitsound": "0", "extras": "0:0:0:0:\n"}, {"x": "448", "y": "192", "time": "104292", "type": "1", "hitsound": "0", "extras": "0:0:0:0:\n"}, {"x": "320", "y": "192", "time": "104407", "type": "128", "hitsound": "4", "extras": "104638:0:0:0:0:\n"}, {"x": "64", "y": "192", "time": "104638", "type": "128", "hitsound": "0", "extras": "104869:0:0:0:0:\n"}, {"x": "448", "y": "192", "time": "104869", "type": "128", "hitsound": "2", "extras": "105100:0:0:0:0:\n"}, {"x": "192", "y": "192", "time": "105100", "type": "128", "hitsound": "0", "extras": "105330:0:0:0:0:\n"}, {"x": "64", "y": "192", "time": "105330", "type": "1", "hitsound": "4", "extras": "0:0:0:0:\n"}, {"x": "320", "y": "192", "time": "105446", "type": "1", "hitsound": "0", "extras": "0:0:0:0:\n"}, {"x": "448", "y": "192", "time": "105561", "type": "1", "hitsound": "0", "extras": "0:0:0:0:\n"}, {"x": "64", "y": "192", "time": "105676", "type": "1", "hitsound": "0", "extras": "0:0:0:0:\n"}, {"x": "192", "y": "192", "time": "105792", "type": "1", "hitsound": "2", "extras": "0:0:0:0:\n"}, {"x": "320", "y": "192", "time": "105907", "type": "1", "hitsound": "0", "extras": "0:0:0:0:\n"}, {"x": "448", "y": "192", "time": "106023", "type": "1", "hitsound": "0", "extras": "0:0:0:0:\n"}, {"x": "64", "y": "192", "time": "106138", "type": "1", "hitsound": "0", "extras": "0:0:0:0:\n"}, {"x": "192", "y": "192", "time": "106253", "type": "128", "hitsound": "4", "extras": "106484:0:0:0:0:\n"}, {"x": "448", "y": "192", "time": "106484", "type": "128", "hitsound": "0", "extras": "106715:0:0:0:0:\n"}, {"x": "320", "y": "192", "time": "106715", "type": "128", "hitsound": "2", "extras": "106946:0:0:0:0:\n"}, {"x": "64", "y": "192", "time": "106946", "type": "128", "hitsound": "0", "extras": "107176:0:0:0:0:\n"}, {"x": "448", "y": "192", "time": "107176", "type": "128", "hitsound": "4", "extras": "107407:0:0:0:0:\n"}, {"x": "192", "y": "192", "time": "107407", "type": "128", "hitsound": "0", "extras": "107638:0:0:0:0:\n"}, {"x": "320", "y": "192", "time": "107638", "type": "1", "hitsound": "2", "extras": "0:0:0:0:\n"}, {"x": "64", "y": "192", "time": "107753", "type": "1", "hitsound": "0", "extras": "0:0:0:0:\n"}, {"x": "448", "y": "192", "time": "107869", "type": "1", "hitsound": "0", "extras": "0:0:0:0:\n"}, {"x": "64", "y": "192", "time": "107984", "type": "1", "hitsound": "0", "extras": "0:0:0:0:\n"}, {"x": "192", "y": "192", "time": "108100", "type": "128", "hitsound": "4", "extras": "108330:0:0:0:0:\n"}, {"x": "448", "y": "192", "time": "108330", "type": "128", "hitsound": "0", "extras": "108561:0:0:0:0:\n"}, {"x": "64", "y": "192", "time": "108561", "type": "128", "hitsound": "2", "extras": "108792:0:0:0:0:\n"}, {"x": "320", "y": "192", "time": "108792", "type": "128", "hitsound": "0", "extras": "109023:0:0:0:0:\n"}, {"x": "448", "y": "192", "time": "109023", "type": "1", "hitsound": "4", "extras": "0:0:0:0:\n"}, {"x": "64", "y": "192", "time": "109138", "type": "1", "hitsound": "0", "extras": "0:0:0:0:\n"}, {"x": "192", "y": "192", "time": "109253", "type": "1", "hitsound": "0", "extras": "0:0:0:0:\n"}, {"x": "448", "y": "192", "time": "109369", "type": "1", "hitsound": "0", "extras": "0:0:0:0:\n"}, {"x": "320", "y": "192", "time": "109484", "type": "1", "hitsound": "4", "extras": "0:0:0:0:\n"}, {"x": "192", "y": "192", "time": "109600", "type": "1", "hitsound": "0", "extras": "0:0:0:0:\n"}, {"x": "448", "y": "192", "time": "109715", "type": "1", "hitsound": "0", "extras": "0:0:0:0:\n"}, {"x": "64", "y": "192", "time": "109830", "type": "1", "hitsound": "0", "extras": "0:0:0:0:\n"}, {"x": "192", "y": "192", "time": "109946", "type": "1", "hitsound": "4", "extras": "0:0:0:0:\n"}, {"x": "320", "y": "192", "time": "110061", "type": "1", "hitsound": "0", "extras": "0:0:0:0:\n"}, {"x": "64", "y": "192", "time": "110176", "type": "1", "hitsound": "0", "extras": "0:0:0:0:\n"}, {"x": "448", "y": "192", "time": "110292", "type": "1", "hitsound": "0", "extras": "0:0:0:0:\n"}, {"x": "192", "y": "192", "time": "110407", "type": "1", "hitsound": "0", "extras": "0:0:0:0:\n"}, {"x": "320", "y": "192", "time": "110523", "type": "1", "hitsound": "0", "extras": "0:0:0:0:\n"}, {"x": "64", "y": "192", "time": "110638", "type": "1", "hitsound": "0", "extras": "0:0:0:0:\n"}, {"x": "448", "y": "192", "time": "110753", "type": "1", "hitsound": "0", "extras": "0:0:0:0:\n"}, {"x": "320", "y": "192", "time": "110869", "type": "128", "hitsound": "4", "extras": "115253:0:0:0:0:\n"}]}